parseargs/__init__.py
parseargs/test.py
parseargs-0.0.5.dist-info/METADATA
parseargs-0.0.5.dist-info/WHEEL
parseargs-0.0.5.dist-info/top_level.txt
parseargs-0.0.5.dist-info/RECORD
