Metadata-Version: 2.1
Name: parseargs
Version: 0.0.5
Summary: A simple package for parsing function arguments from the command line
Home-page: https://github.com/AndrewNolte/ParseArgs
Author: Andrew Nolte
Author-email: anolte512@gmail.com
License: UNKNOWN
Platform: UNKNOWN
Classifier: Programming Language :: Python :: 3
Classifier: License :: OSI Approved :: MIT License
Classifier: Operating System :: OS Independent
Requires-Python: >=3.6
